activityrelay-0.3.5.dist-info/licenses/LICENSE
relay/__init__.py
relay/__main__.py
relay/api_objects.py
relay/cache.py
relay/compat.py
relay/config.py
relay/http_client.py
relay/logger.py
relay/misc.py
relay/processors.py
relay/py.typed
relay/state.py
relay/template.py
relay/workers.py
relay/cli/__init__.py
relay/cli/ban.py
relay/cli/base.py
relay/cli/config.py
relay/cli/inbox.py
relay/cli/instance_ban.py
relay/cli/request.py
relay/cli/software_ban.py
relay/cli/user.py
relay/cli/whitelist.py
relay/data/statements.sql
relay/database/__init__.py
relay/database/config.py
relay/database/connection.py
relay/database/schema.py
relay/frontend/base.haml
relay/frontend/functions.haml
relay/frontend/variables.css
relay/frontend/page/authorize_new.haml
relay/frontend/page/authorize_show.haml
relay/frontend/page/docs.haml
relay/frontend/page/error.haml
relay/frontend/page/home.haml
relay/frontend/page/login.haml
relay/frontend/page/admin/config.haml
relay/frontend/page/admin/domain_bans.haml
relay/frontend/page/admin/instances.haml
relay/frontend/page/admin/software_bans.haml
relay/frontend/page/admin/whitelist.haml
relay/frontend/static/bootstrap-icons.css
relay/frontend/static/bootstrap-icons.woff2
relay/frontend/static/functions.js
relay/frontend/static/style.css
relay/views/__init__.py
relay/views/activitypub.py
relay/views/api.py
relay/views/base.py
relay/views/frontend.py
relay/views/middleware.py
relay/views/misc.py
activityrelay-0.3.5.dist-info/METADATA
activityrelay-0.3.5.dist-info/WHEEL
activityrelay-0.3.5.dist-info/entry_points.txt
activityrelay-0.3.5.dist-info/top_level.txt
activityrelay-0.3.5.dist-info/RECORD
