Metadata-Version: 2.4
Name: ActivityRelay
Version: 0.3.5
Summary: Generic LitePub relay (works with all LitePub consumers and Mastodon)
License: GNU AFFERO GENERAL PUBLIC LICENSE
Project-URL: Documentation, https://git.pleroma.social/pleroma/relay/-/blob/main/docs/index.md
Project-URL: Source, https://git.pleroma.social/pleroma/relay
Classifier: Development Status :: 4 - Beta
Classifier: Environment :: Console
Classifier: Framework :: aiohttp
Classifier: Framework :: AsyncIO
Classifier: License :: OSI Approved :: GNU Affero General Public License v3
Classifier: Programming Language :: Python
Classifier: Programming Language :: Python :: 3.10
Classifier: Programming Language :: Python :: 3.11
Classifier: Programming Language :: Python :: 3.12
Classifier: Programming Language :: Python :: 3.13
Classifier: Programming Language :: SQL
Classifier: Topic :: Internet :: WWW/HTTP :: HTTP Servers
Classifier: Typing :: Typed
Requires-Python: >=3.10
License-File: LICENSE
Requires-Dist: activitypub-utils<0.4,>=0.3.2
Requires-Dist: aiohttp>=3.9.5
Requires-Dist: argon2-cffi==23.1.0
Requires-Dist: barkshark-lib<0.3.0,>=0.2.5.post1
Requires-Dist: barkshark-sql<0.3.0,>=0.2.0
Requires-Dist: click==8.1.2
Requires-Dist: docstring-parser==0.16
Requires-Dist: hamlish==0.4.0
Requires-Dist: hiredis==2.3.2
Requires-Dist: idna==3.4
Requires-Dist: markdown==3.6
Requires-Dist: platformdirs==4.2.2
Requires-Dist: pyyaml==6.0.1
Requires-Dist: redis==5.0.7
Provides-Extra: performance
Requires-Dist: uvloop==0.21.1; extra == "performance"
Provides-Extra: dev
Requires-Dist: flake8==7.1.1; extra == "dev"
Requires-Dist: mypy==1.13.0; extra == "dev"
Requires-Dist: pyinstaller==6.10.0; extra == "dev"
Requires-Dist: typing-extensions==4.12.2; python_version < "3.11" and extra == "dev"
Dynamic: license-file
